MANIFEST.in
README.rst
setup.py
docs/HISTORY.txt
docs/LICENSE.GPL
docs/LICENSE.txt
ftw/__init__.py
ftw.file.egg-info/PKG-INFO
ftw.file.egg-info/SOURCES.txt
ftw.file.egg-info/dependency_links.txt
ftw.file.egg-info/entry_points.txt
ftw.file.egg-info/namespace_packages.txt
ftw.file.egg-info/not-zip-safe
ftw.file.egg-info/requires.txt
ftw.file.egg-info/top_level.txt
ftw/file/__init__.py
ftw/file/config.py
ftw/file/configure.zcml
ftw/file/custom_outputfilter.py
ftw/file/fields.py
ftw/file/handlers.py
ftw/file/hooks.py
ftw/file/indexer.py
ftw/file/interfaces.py
ftw/file/lawgiver.zcml
ftw/file/overrides.zcml
ftw/file/permissions.zcml
ftw/file/resources.zcml
ftw/file/testing.py
ftw/file/utils.py
ftw/file/Extensions/__init__.py
ftw/file/Extensions/install.py
ftw/file/activity2/__init__.py
ftw/file/activity2/configure.zcml
ftw/file/activity2/subscribers.py
ftw/file/browser/__init__.py
ftw/file/browser/activity.pt
ftw/file/browser/activity.py
ftw/file/browser/configure.zcml
ftw/file/browser/download.py
ftw/file/browser/edit_form.py
ftw/file/browser/file_view.pt
ftw/file/browser/file_view.py
ftw/file/browser/upload.py
ftw/file/browser/resources/file.scss
ftw/file/content/__init__.py
ftw/file/content/configure.zcml
ftw/file/content/dxfile.py
ftw/file/content/file.py
ftw/file/events/__init__.py
ftw/file/events/events.py
ftw/file/locales/ftw.activity.pot
ftw/file/locales/ftw.file.pot
ftw/file/locales/plone.pot
ftw/file/locales/de/LC_MESSAGES/ftw.activity.po
ftw/file/locales/de/LC_MESSAGES/ftw.file.po
ftw/file/locales/de/LC_MESSAGES/plone.po
ftw/file/locales/en/LC_MESSAGES/ftw.activity.po
ftw/file/locales/en/LC_MESSAGES/ftw.file.po
ftw/file/locales/en/LC_MESSAGES/plone.po
ftw/file/locales/fr/LC_MESSAGES/ftw.activity.po
ftw/file/locales/fr/LC_MESSAGES/ftw.file.po
ftw/file/locales/fr/LC_MESSAGES/plone.po
ftw/file/profiles/default/catalog.xml
ftw/file/profiles/default/cssregistry.xml
ftw/file/profiles/default/jsregistry.xml
ftw/file/profiles/default/metadata.xml
ftw/file/profiles/default/registry.xml
ftw/file/profiles/default/repositorytool.xml
ftw/file/profiles/default/rolemap.xml
ftw/file/profiles/default/types.xml
ftw/file/profiles/default/types/ftw.file.File.xml
ftw/file/profiles/default_plone5/catalog.xml
