Metadata-Version: 2.1
Name: ftw.file
Version: 2.6.4
Summary: A file content type for gov usecases
Home-page: https://github.com/4teamwork/ftw.file
Author: 4teamwork AG
Author-email: mailto:info@4teamwork.ch
License: GPL2
Keywords: plone file contenttype
Platform: UNKNOWN
Classifier: Framework :: Plone
Classifier: Framework :: Plone :: 4.3
Classifier: Framework :: Plone :: 5.1
Classifier: Programming Language :: Python
Classifier: Topic :: Software Development :: Libraries :: Python Modules
Provides-Extra: tests
